nbviewer/__init__.py
nbviewer/__main__.py
nbviewer/_version.py
nbviewer/app.py
nbviewer/cache.py
nbviewer/formats.py
nbviewer/frontpage.json
nbviewer/handlers.py
nbviewer/index.py
nbviewer/log.py
nbviewer/ratelimit.py
nbviewer/render.py
nbviewer/utils.py
nbviewer/providers/__init__.py
nbviewer/providers/base.py
nbviewer/providers/__pycache__/__init__.cpython-35.pyc
nbviewer/providers/__pycache__/__init__.cpython-36.pyc
nbviewer/providers/__pycache__/base.cpython-35.pyc
nbviewer/providers/__pycache__/base.cpython-36.pyc
nbviewer/providers/dropbox/__init__.py
nbviewer/providers/dropbox/handlers.py
nbviewer/providers/dropbox/__pycache__/__init__.cpython-35.pyc
nbviewer/providers/dropbox/__pycache__/__init__.cpython-36.pyc
nbviewer/providers/dropbox/__pycache__/handlers.cpython-35.pyc
nbviewer/providers/dropbox/__pycache__/handlers.cpython-36.pyc
nbviewer/providers/gist/__init__.py
nbviewer/providers/gist/handlers.py
nbviewer/providers/gist/__pycache__/__init__.cpython-35.pyc
nbviewer/providers/gist/__pycache__/__init__.cpython-36.pyc
nbviewer/providers/gist/__pycache__/handlers.cpython-35.pyc
nbviewer/providers/gist/__pycache__/handlers.cpython-36.pyc
nbviewer/providers/gist/tests/__init__.py
nbviewer/providers/gist/tests/test_gist.py
nbviewer/providers/gist/tests/__pycache__/__init__.cpython-35.pyc
nbviewer/providers/gist/tests/__pycache__/__init__.cpython-36.pyc
nbviewer/providers/gist/tests/__pycache__/test_gist.cpython-35.pyc
nbviewer/providers/gist/tests/__pycache__/test_gist.cpython-36.pyc
nbviewer/providers/github/__init__.py
nbviewer/providers/github/client.py
nbviewer/providers/github/handlers.py
nbviewer/providers/github/__pycache__/__init__.cpython-35.pyc
nbviewer/providers/github/__pycache__/__init__.cpython-36.pyc
nbviewer/providers/github/__pycache__/client.cpython-35.pyc
nbviewer/providers/github/__pycache__/client.cpython-36.pyc
nbviewer/providers/github/__pycache__/handlers.cpython-35.pyc
nbviewer-1.0.1.dist-info/DESCRIPTION.rst
nbviewer-1.0.1.dist-info/METADATA
nbviewer-1.0.1.dist-info/RECORD
nbviewer-1.0.1.dist-info/WHEEL
nbviewer-1.0.1.dist-info/metadata.json
nbviewer-1.0.1.dist-info/top_level.txt
