Metadata-Version: 2.0
Name: nbviewer
Version: 1.0.1
Summary: Jupyter Notebook Viewer
Home-page: https://nbviewer.jupyter.org
Author: The Jupyter Development Team
Author-email: jupyter@googlegroups.com
License: BSD
Platform: UNKNOWN
Classifier: License :: OSI Approved :: BSD License
Classifier: Programming Language :: Python :: 2
Classifier: Programming Language :: Python :: 2.7
Classifier: Programming Language :: Python :: 3
Classifier: Programming Language :: Python :: 3.3
Requires-Dist: elasticsearch
Requires-Dist: futures
Requires-Dist: ipython
Requires-Dist: jupyter-client
Requires-Dist: markdown
Requires-Dist: nbconvert (>=5.2.1)
Requires-Dist: nbformat (>=4.2)
Requires-Dist: newrelic (!=2.80.0.60)
Requires-Dist: pycurl
Requires-Dist: pylibmc
Requires-Dist: statsd
Requires-Dist: tornado
